flask_cmless/__init__.py
flask_cmless/models.py
flask_cmless-0.1.0.dist-info/licenses/LICENSE
flask_cmless-0.1.0.dist-info/METADATA
flask_cmless-0.1.0.dist-info/WHEEL
flask_cmless-0.1.0.dist-info/top_level.txt
flask_cmless-0.1.0.dist-info/RECORD
